compass/__init__.py
compass/generator.py
compass/helpers.py
compass/node.py
compass/py.typed
compass/ranker.py
compass/triggers.py
langgraph_compass-1.0.1.dist-info/METADATA
langgraph_compass-1.0.1.dist-info/WHEEL
langgraph_compass-1.0.1.dist-info/licenses/LICENSE
langgraph_compass-1.0.1.dist-info/RECORD
