Metadata-Version: 2.4
Name: langgraph-compass
Version: 1.0.1
Summary: Intelligent follow-up question generation for LangGraph agents
Project-URL: Homepage, https://github.com/sardanaaman/langgraph-compass
Project-URL: Documentation, https://github.com/sardanaaman/langgraph-compass#readme
Project-URL: Repository, https://github.com/sardanaaman/langgraph-compass
Project-URL: Issues, https://github.com/sardanaaman/langgraph-compass/issues
Author: Aman Sardana
License: Apache-2.0
License-File: LICENSE
Keywords: agents,conversational-ai,follow-up,langchain,langgraph,llm,questions
Classifier: Development Status :: 4 - Beta
Classifier: Intended Audience :: Developers
Classifier: License :: OSI Approved :: Apache Software License
Classifier: Programming Language :: Python :: 3
Classifier: Programming Language :: Python :: 3.11
Classifier: Programming Language :: Python :: 3.12
Classifier: Programming Language :: Python :: 3.13
Classifier: Topic :: Scientific/Engineering :: Artificial Intelligence
Requires-Python: >=3.11
Requires-Dist: langchain-core>=0.3.0
Requires-Dist: langchain-openai>=1.1.7
Requires-Dist: langgraph>=0.2.0
Requires-Dist: pydantic>=2.0.0
Provides-Extra: dev
Requires-Dist: mypy>=1.14.0; extra == 'dev'
Requires-Dist: pre-commit>=4.0.0; extra == 'dev'
Requires-Dist: pytest-asyncio>=0.24.0; extra == 'dev'
Requires-Dist: pytest>=8.0.0; extra == 'dev'
Requires-Dist: ruff>=0.9.0; extra == 'dev'
